voidlight_choreographer.py
voidlight_choreographer-0.1.2.dist-info/licenses/LICENSE.txt
voidlight_choreographer-0.1.2.dist-info/METADATA
voidlight_choreographer-0.1.2.dist-info/WHEEL
voidlight_choreographer-0.1.2.dist-info/entry_points.txt
voidlight_choreographer-0.1.2.dist-info/top_level.txt
voidlight_choreographer-0.1.2.dist-info/RECORD
