Metadata-Version: 2.4
Name: voidlight_choreographer
Version: 0.1.2
Summary: BDSM space-pirate commit planner and preview engine
Author-email: Velvet Chains Maintainers <snark@voidlight.dev>
License: MIT
Project-URL: Homepage, https://github.com/hsmalley/velvet-chains
Project-URL: Repository, https://github.com/hsmalley/velvet-chains
Keywords: git,commit,cli,nsfw,space-pirate
Classifier: Development Status :: 4 - Beta
Classifier: Programming Language :: Python :: 3
Classifier: Programming Language :: Python :: 3.12
Classifier: License :: OSI Approved :: MIT License
Classifier: Environment :: Console
Classifier: Topic :: Software Development :: Version Control
Requires-Python: >=3.12
License-File: LICENSE.txt
Requires-Dist: pyyaml>=6.0.3
Dynamic: license-file
